mcp_simple_openai_assistant/__init__.py
mcp_simple_openai_assistant/__main__.py
mcp_simple_openai_assistant/app.py
mcp_simple_openai_assistant/assistant_manager.py
mcp_simple_openai_assistant/thread_store.py
mseep_mcp_simple_openai_assistant-0.4.2.dist-info/licenses/LICENSE
mseep_mcp_simple_openai_assistant-0.4.2.dist-info/METADATA
mseep_mcp_simple_openai_assistant-0.4.2.dist-info/WHEEL
mseep_mcp_simple_openai_assistant-0.4.2.dist-info/entry_points.txt
mseep_mcp_simple_openai_assistant-0.4.2.dist-info/top_level.txt
mseep_mcp_simple_openai_assistant-0.4.2.dist-info/RECORD
